morphius/__init__.py
morphius/cli/__init__.py
morphius/cli/cli.py
morphius/cli/console_output.py
morphius/cli/planner.py
morphius/cli/providers.py
morphius/cli/runner.py
morphius/cli/scoping.py
morphius/config/__init__.py
morphius/config/globals.py
morphius/config/providers.py
morphius/core/__init__.py
morphius/core/base/__init__.py
morphius/core/base/evaluator.py
morphius/core/builders/__init__.py
morphius/core/builders/provider_vars.py
morphius/core/builders/redteam.py
morphius/core/converters/__init__.py
morphius/core/converters/prompts.py
morphius/core/converters/providers/__init__.py
morphius/core/engine/__init__.py
morphius/core/engine/evaluator.py
morphius/core/engine/results.py
morphius/core/engine/vanilla.py
morphius/core/engine/vanilla_multiturn.py
morphius/core/exceptions/__init__.py
morphius/core/exceptions/agents.py
morphius/core/exceptions/base.py
morphius/core/exceptions/evaluator.py
morphius/core/models/__init__.py
morphius/core/models/analysis.py
morphius/core/models/base.py
morphius/core/models/evaluator.py
morphius/core/models/plugins.py
morphius/core/models/prompts.py
morphius/core/models/providers/__init__.py
morphius/core/models/providers/base.py
morphius/core/models/providers/gradio.py
morphius/core/models/providers/hf.py
morphius/core/models/providers/http.py
morphius/core/models/providers/ollama.py
morphius/core/models/results.py
morphius/core/models/scope.py
morphius/core/models/tactic.py
morphius/core/models/target.py
morphius/core/repo/__init__.py
morphius/core/repo/hf_models.yml
morphius/core/repo/plugin.py
morphius/core/repo/plugins.yml
morphius/core/repo/plugins.yml.bak
morphius/core/repo/taxonomy.yml
morphius/experimental/__init__.py
morphius/experimental/generate_risks.py
morphius/plugins/__init__.py
morphius/plugins/agents/__init__.py
morphius/plugins/agents/autogen/__init__.py
morphius/plugins/agents/autogen/agents_scope_generator.py
morphius/plugins/agents/autogen/utils/__init__.py
morphius/plugins/agents/autogen/utils/console.py
morphius-0.10.0.dist-info/METADATA
morphius-0.10.0.dist-info/WHEEL
morphius-0.10.0.dist-info/entry_points.txt
morphius-0.10.0.dist-info/RECORD
